setup.py
brynq_sdk_dynamics/__init__.py
brynq_sdk_dynamics/dynamics.py
brynq_sdk_dynamics.egg-info/PKG-INFO
brynq_sdk_dynamics.egg-info/SOURCES.txt
brynq_sdk_dynamics.egg-info/dependency_links.txt
brynq_sdk_dynamics.egg-info/not-zip-safe
brynq_sdk_dynamics.egg-info/requires.txt
brynq_sdk_dynamics.egg-info/top_level.txt