Metadata-Version: 1.0
Name: brynq-sdk-dynamics
Version: 1.0.0
Summary: Dynamics wrapper from BrynQ
Home-page: UNKNOWN
Author: BrynQ
Author-email: support@brynq.com
License: BrynQ License
Platform: UNKNOWN
